mooda/__init__.py
mooda/archive.py
mooda/assembly.py
mooda/cli.py
mooda/commands.py
mooda/config.py
mooda/dna_component.py
mooda/evolutionary_algorithm.py
mooda/individual.py
mooda/io.py
mooda/montecarlo_algorithm.py
mooda/objective_function.py
mooda/operator.py
mooda/population.py
mooda/utils.py
mooda_dna-0.11.0.dist-info/LICENSE
mooda_dna-0.11.0.dist-info/METADATA
mooda_dna-0.11.0.dist-info/WHEEL
mooda_dna-0.11.0.dist-info/entry_points.txt
mooda_dna-0.11.0.dist-info/top_level.txt
mooda_dna-0.11.0.dist-info/RECORD
