Metadata-Version: 2.1
Name: mooda-dna
Version: 0.11.0
Summary: A Multi-Objective algorithm for DNA Design and Assembly
Home-page: https://github.com/stracquadaniolab/mooda
Author: Angelo Gaeta, Giovanni Stracquadanio
Author-email: a.gaeta@sms.ed.ac.uk
License: MIT
Platform: UNKNOWN
Classifier: License :: OSI Approved :: MIT License
Classifier: Programming Language :: Python :: 3.7
Classifier: Topic :: Scientific/Engineering :: Bio-Informatics
Requires-Dist: biopython (==1.73)
Requires-Dist: numpy (==1.16.2)
Requires-Dist: pandas (==0.24.2)
Requires-Dist: PyYAML (==5.4)
Requires-Dist: tqdm
